netmon_proc/__init__.py
netmon_proc/__main__.py
netmon_proc/cli/__init__.py
netmon_proc/cli/logger.py
netmon_proc/cli/opts.py
netmon_proc/cli/utils.py
netmon_proc/formatter/__init__.py
netmon_proc/formatter/format.py
netmon_proc/formatter/jsonmetricsformatter.py
netmon_proc/formatter/metricsformatter.py
netmon_proc/formatter/metricsformatterfactory.py
netmon_proc/formatter/tablemetricsformatter.py
netmon_proc/formatter/utils.py
netmon_proc/main.py
netmon_proc/metrics/__init__.py
netmon_proc/metrics/compositemetric.py
netmon_proc/metrics/leafmetric.py
netmon_proc/metrics/metric.py
netmon_proc/metrics/metricsfactory.py
netmon_proc/metrics/metrictype.py
netmon_proc/metrics/rxbytesmetric.py
netmon_proc/metrics/rxpacketsmetric.py
netmon_proc/metrics/txbytesmetric.py
netmon_proc/metrics/txpacketsmetric.py
netmon_proc/netinfo.py
netmon_proc/patterns/singleton.py
netmon_proc/sniffer.py
netmon_proc/socketwatcher/__init__.py
netmon_proc/socketwatcher/fetchingexception.py
netmon_proc/socketwatcher/fetchingstrategy.py
netmon_proc/socketwatcher/psutilfetchingstrategy.py
netmon_proc/socketwatcher/socket.py
netmon_proc/socketwatcher/socketwatcher.py
netmon_proc/utils.py
netmon_proc-0.2.11.dist-info/LICENSE
netmon_proc-0.2.11.dist-info/METADATA
netmon_proc-0.2.11.dist-info/WHEEL
netmon_proc-0.2.11.dist-info/entry_points.txt
netmon_proc-0.2.11.dist-info/RECORD
